deutschland/EcoVisio/__init__.py
deutschland/EcoVisio/api/__init__.py
deutschland/EcoVisio/api/default_api.py
deutschland/EcoVisio/api_client.py
deutschland/EcoVisio/apis/__init__.py
deutschland/EcoVisio/configuration.py
deutschland/EcoVisio/exceptions.py
deutschland/EcoVisio/model/__init__.py
deutschland/EcoVisio/model/all_counter.py
deutschland/EcoVisio/model/all_counter_inner.py
deutschland/EcoVisio/model/all_counter_inner_photo_inner.py
deutschland/EcoVisio/model/all_counter_inner_pratique_inner.py
deutschland/EcoVisio/model/date.py
deutschland/EcoVisio/model_utils.py
deutschland/EcoVisio/models/__init__.py
deutschland/EcoVisio/rest.py
de_ecovisio-0.1.0.dist-info/WHEEL
de_ecovisio-0.1.0.dist-info/METADATA
de_ecovisio-0.1.0.dist-info/RECORD
